MANIFEST.in
crm_claim_data.xml
crm_claim_demo.xml
crm_claim_menu.xml
crm_claim_view.xml
res_config_view.xml
setup.py
./__init__.py
./__openerp__.py
./crm_claim.py
./res_config.py
./report/__init__.py
./report/crm_claim_report.py
i18n/ar.po
i18n/bg.po
i18n/bs.po
i18n/ca.po
i18n/crm_claim.pot
i18n/cs.po
i18n/da.po
i18n/de.po
i18n/el.po
i18n/es.po
i18n/es_CR.po
i18n/es_EC.po
i18n/es_MX.po
i18n/es_PY.po
i18n/es_VE.po
i18n/fi.po
i18n/fr.po
i18n/gl.po
i18n/gu.po
i18n/hr.po
i18n/hu.po
i18n/it.po
i18n/ja.po
i18n/ko.po
i18n/lt.po
i18n/mk.po
i18n/mn.po
i18n/nb.po
i18n/nl.po
i18n/pl.po
i18n/pt.po
i18n/pt_BR.po
i18n/ro.po
i18n/ru.po
i18n/sl.po
i18n/sq.po
i18n/sr.po
i18n/sr@latin.po
i18n/sv.po
i18n/tr.po
i18n/zh_CN.po
i18n/zh_TW.po
images/claim_categories.jpeg
images/claim_stages.jpeg
images/claims.jpeg
openerp_crm_claim.egg-info/PKG-INFO
openerp_crm_claim.egg-info/SOURCES.txt
openerp_crm_claim.egg-info/dependency_links.txt
openerp_crm_claim.egg-info/requires.txt
openerp_crm_claim.egg-info/top_level.txt
report/crm_claim_report_view.xml
security/ir.model.access.csv
test/customer_claim.eml
test/process/claim.yml
test/ui/claim_demo.yml